expnbk/__init__.py
expnbk/example.py
expnbk/experiment.py
expnbk-0.0.3.dist-info/LICENSE
expnbk-0.0.3.dist-info/METADATA
expnbk-0.0.3.dist-info/WHEEL
expnbk-0.0.3.dist-info/top_level.txt
expnbk-0.0.3.dist-info/RECORD
