Metadata-Version: 2.1
Name: expnbk
Version: 0.0.3
Summary: expnbk provides a class for creating an experiment with its own results directory that automatically contains a copy of the code used to run the experiment. Super useful for reproducibility.
Home-page: https://github.com/KaiyanPengNJU/Experiment_Notebook
Author: Kaiyan Peng
Author-email: kaiyanpeng@gmail.com
License: MIT
Keywords: expnbk
Platform: UNKNOWN
Classifier: Development Status :: 2 - Pre-Alpha
Classifier: Intended Audience :: Science/Research 
Classifier: License :: OSI Approved :: MIT License
Classifier: Natural Language :: English
Classifier: Programming Language :: Python
Classifier: Programming Language :: Python :: 3
Classifier: Programming Language :: Python :: 3 :: Only
Classifier: Programming Language :: Python :: 3.6
Classifier: Programming Language :: Python :: 3.7
Classifier: Programming Language :: Python :: 3.8
Classifier: Topic :: Scientific/Engineering
Requires-Python: >=3.6
Requires-Dist: matplotlib
Provides-Extra: all
Requires-Dist: matplotlib ; extra == 'all'
Requires-Dist: bump2version (>=1.0.0) ; extra == 'all'
Requires-Dist: ipython (>=7.5.0) ; extra == 'all'
Requires-Dist: twine (>=1.13.0) ; extra == 'all'
Requires-Dist: wheel (>=0.33.1) ; extra == 'all'
Provides-Extra: dev
Requires-Dist: bump2version (>=1.0.0) ; extra == 'dev'
Requires-Dist: ipython (>=7.5.0) ; extra == 'dev'
Requires-Dist: twine (>=1.13.0) ; extra == 'dev'
Requires-Dist: wheel (>=0.33.1) ; extra == 'dev'
Provides-Extra: docs
Provides-Extra: setup
Provides-Extra: test
